LICENSE
MANIFEST.in
README.md
setup.py
chatpilot/__init__.py
chatpilot/agentica_agent.py
chatpilot/config.py
chatpilot/constants.py
chatpilot/server.py
chatpilot/version.py
chatpilot.egg-info/PKG-INFO
chatpilot.egg-info/SOURCES.txt
chatpilot.egg-info/dependency_links.txt
chatpilot.egg-info/entry_points.txt
chatpilot.egg-info/not-zip-safe
chatpilot.egg-info/requires.txt
chatpilot.egg-info/top_level.txt
chatpilot/apps/__init__.py
chatpilot/apps/audio_app.py
chatpilot/apps/auth_utils.py
chatpilot/apps/dashscope_app.py
chatpilot/apps/db.py
chatpilot/apps/image_app.py
chatpilot/apps/litellm_app.py
chatpilot/apps/misc.py
chatpilot/apps/ollama_app.py
chatpilot/apps/openai_app.py
chatpilot/apps/rag_app.py
chatpilot/apps/rag_utils.py
chatpilot/apps/web_app.py
chatpilot/apps/web/__init__.py