Metadata-Version: 2.1
Name: chatpilot
Version: 1.0.1
Summary: Chat Agent toolkit.
Home-page: https://github.com/shibing624/chatpilot
Author: XuMing
Author-email: xuming624@qq.com
License: Apache License 2.0
Keywords: llm,agent
Classifier: Development Status :: 5 - Production/Stable
Classifier: Intended Audience :: Developers
Classifier: Intended Audience :: Education
Classifier: Intended Audience :: Science/Research
Classifier: License :: OSI Approved :: Apache Software License
Classifier: Operating System :: OS Independent
Classifier: Programming Language :: Python :: 3
Classifier: Topic :: Scientific/Engineering :: Artificial Intelligence
Requires-Python: >=3.9.0
License-File: LICENSE
Requires-Dist: loguru
Requires-Dist: tiktoken
Requires-Dist: langchain~=0.1.11
Requires-Dist: langchain-community~=0.0.27
Requires-Dist: langchain-openai~=0.0.8
Requires-Dist: openai~=1.13.3
